ohdsi_cdm_loader/__init__.py
ohdsi_cdm_loader/db_connector.py
ohdsi_cdm_loader/load_csv.py
cdm_csv_loader-0.2.0.dist-info/METADATA
cdm_csv_loader-0.2.0.dist-info/WHEEL
cdm_csv_loader-0.2.0.dist-info/top_level.txt
cdm_csv_loader-0.2.0.dist-info/RECORD
