Metadata-Version: 2.2
Name: cdm_csv_loader
Version: 0.2.0
Summary: A package for loading OHDSI CDM CSV files into a relational database.
Home-page: https://github.com/DavidIkechi/ohdsi_cdm_loader.git
Author: David Chibuike Ikechi Akwuru, Jeremiah Akintomide
Author-email: akwuru.david@ul.ie, akintomide.jeremiah@ul.ie
Maintainer: David Chibuike Ikechi Akwuru, Jeremiah Akintomide
Maintainer-email: akwuru.david@ul.ie, akintomide.jeremiah@ul.ie
License: MIT
Classifier: Programming Language :: Python :: 3
Classifier: License :: OSI Approved :: MIT License
Classifier: Operating System :: OS Independent
Requires-Python: >=3.9
Requires-Dist: pandas>=1.0.0
Requires-Dist: rpy2==3.5.12
Dynamic: author
Dynamic: author-email
Dynamic: classifier
Dynamic: description
Dynamic: description-content-type
Dynamic: home-page
Dynamic: license
Dynamic: maintainer
Dynamic: maintainer-email
Dynamic: requires-dist
Dynamic: requires-python
Dynamic: summary
